MANIFEST.in
README.rst
setup.py
helloworld1995/__init__.py
helloworld1995/helloworld.py
helloworld1995.egg-info/PKG-INFO
helloworld1995.egg-info/SOURCES.txt
helloworld1995.egg-info/dependency_links.txt
helloworld1995.egg-info/entry_points.txt
helloworld1995.egg-info/not-zip-safe
helloworld1995.egg-info/top_level.txt