Metadata-Version: 1.1
Name: helloworld1995
Version: 0.13
Summary: A hello world program to investigate packaging and PyPI
Home-page: UNKNOWN
Author: Jaye Heffernan
Author-email: jayejaye@live.com.au
License: MIT
Platform: UNKNOWN
Classifier: Programming Language :: Python :: 3.5
